ucdp_ipxact-0.2.0.dist-info/METADATA
ucdp_ipxact-0.2.0.dist-info/WHEEL
ucdp_ipxact-0.2.0.dist-info/entry_points.txt
ucdp_ipxact-0.2.0.dist-info/licenses/LICENSE
ucdp_ipxact/__init__.py
ucdp_ipxact/cli.py
ucdp_ipxact/ipxact.py
ucdp_ipxact/mod.py
ucdp_ipxact/parser.py
ucdp_ipxact/parsermanager.py
ucdp_ipxact/spirit_1685_2009/parser.py
ucdp_ipxact/spirit_1685_2009/xml_schema/abstractionDefinition.xsd
ucdp_ipxact/spirit_1685_2009/xml_schema/abstractor.xsd
ucdp_ipxact/spirit_1685_2009/xml_schema/autoConfigure.xsd
ucdp_ipxact/spirit_1685_2009/xml_schema/busDefinition.xsd
ucdp_ipxact/spirit_1685_2009/xml_schema/busInterface.xsd
ucdp_ipxact/spirit_1685_2009/xml_schema/commonStructures.xsd
ucdp_ipxact/spirit_1685_2009/xml_schema/component.xsd
ucdp_ipxact/spirit_1685_2009/xml_schema/configurable.xsd
ucdp_ipxact/spirit_1685_2009/xml_schema/constraints.xsd
ucdp_ipxact/spirit_1685_2009/xml_schema/design.xsd
ucdp_ipxact/spirit_1685_2009/xml_schema/designConfig.xsd
ucdp_ipxact/spirit_1685_2009/xml_schema/file.xsd
ucdp_ipxact/spirit_1685_2009/xml_schema/fileType.xsd
ucdp_ipxact/spirit_1685_2009/xml_schema/generator.xsd
ucdp_ipxact/spirit_1685_2009/xml_schema/identifier.xsd
ucdp_ipxact/spirit_1685_2009/xml_schema/index.xsd
ucdp_ipxact/spirit_1685_2009/xml_schema/memoryMap.xsd
ucdp_ipxact/spirit_1685_2009/xml_schema/model.xsd
ucdp_ipxact/spirit_1685_2009/xml_schema/port.xsd
ucdp_ipxact/spirit_1685_2009/xml_schema/signalDrivers.xsd
ucdp_ipxact/spirit_1685_2009/xml_schema/simpleTypes.xsd
ucdp_ipxact/spirit_1685_2009/xml_schema/subInstances.xsd
ucdp_ipxact/spirit_1685_2009/xml_schema_pkg.py
ucdp_ipxact-0.2.0.dist-info/RECORD
