Metadata-Version: 2.1
Name: ucdp-ipxact
Version: 0.2.0
Summary: Unified Chip Design Platform - IPXACT
Classifier: Programming Language :: Python :: 3
Classifier: Operating System :: OS Independent
Project-URL: Homepage, https://github.com/nbiotcloud/ucdp-ipxact
Project-URL: Documentation, https://ucdp-ipxact.readthedocs.io/en/stable/
Project-URL: Bug tracker, https://github.com/nbiotcloud/ucdp-ipxact/issues
Requires-Python: <4.0,>=3.10.0
Requires-Dist: ucdp>=0.11.0
Requires-Dist: ucdp-glbl>=0.5.0
Requires-Dist: xsdata[cli,lxml,soap]>=24.5
Requires-Dist: xmlschema>=3.3.1
Requires-Dist: defusedxml>=0.7.1
Requires-Dist: ucdp-addr>=1.0.1
